pdcontextevents/__init__.py
pdcontextevents/allevents.py
pdcontextevents/events.py
pdcontextevents-0.0.9.dist-info/METADATA
pdcontextevents-0.0.9.dist-info/WHEEL
pdcontextevents-0.0.9.dist-info/license.txt
pdcontextevents-0.0.9.dist-info/top_level.txt
pdcontextevents-0.0.9.dist-info/RECORD
