Metadata-Version: 2.1
Name: pdcontextevents
Version: 0.0.9
Summary: initialize constants
Author: GoldFincher14344
License-File: license.txt
